py_spacy_redact_message/__init__.py
py_spacy_redact_message/main.py
py_spacy_redact_message-0.0.28.dist-info/LICENSE
py_spacy_redact_message-0.0.28.dist-info/METADATA
py_spacy_redact_message-0.0.28.dist-info/WHEEL
py_spacy_redact_message-0.0.28.dist-info/entry_points.txt
py_spacy_redact_message-0.0.28.dist-info/top_level.txt
py_spacy_redact_message-0.0.28.dist-info/RECORD
