Metadata-Version: 2.1
Name: py-spacy-redact-message
Version: 0.0.28
Summary: Redact a PHI (personal health
Author: Alex Ilin
Author-email: ilin.alex.mail@gmail.com
License: MIT
Classifier: Programming Language :: Python :: 3
License-File: LICENSE
Requires-Dist: typer
Requires-Dist: spacy
